{
	"spider": "https://raw.gitmirror.com/T00700/TVBoxSE/master/FongMi.jar;md5;FDB39048BFED72C40BFF44A039A6582A",
	"wallpaper": "https://raw.gitmirror.com/T00700/TVBoxSE/master/Wallpaper/01.jpg",
	"lives": [{
			"name": "毫秒直播",
			"type": 0,
			"playerType": 1,
			"boot": false,
			"timeout": 5,
			"url": "https://raw.gitmirror.com/T00700/TVBoxSE/master/live.txt"
		},
		{
			"name": "港台直播",
			"type": 0,
			"playerType": 2,
			"boot": false,
			"timeout": 10,
			"url": "https://raw.gitmirror.com/T00700/TVBoxSE/master/qt.txt"
		},
		{
			"name": "私立直播",
			"type": 0,
			"playerType": 1,
			"boot": false,
			"timeout": 5,
			"url": "https://gh.con.sh/https://raw.githubusercontent.com/ssili126/tv/main/itvlist.txt"
		},
		{
			"name": "iptv6直播",
			"type": 0,
			"playerType": 1,
			"boot": false,
			"timeout": 5,
			"url": "https://fanmingming.com/txt?url=https://live.fanmingming.com/tv/m3u/ipv6.m3u",
			"ua": "okhttp/3.15"
		}

	],
	"sites": [{
			"key": "黑木耳源",
			"name": "黑木耳源",
			"type": 0,
			"api": "https://xml.heimuer.tv/api.php/provide/vod/at/xml/?ac=list",
			"searchable": 1,
			"quickSearch": 1,
			"filterable": 1,
			"changeable": 1,
			"categories": ["国产剧", "国产综艺", "韩剧", "喜剧", "剧情", "爱情", "科幻", "惊悚", "动画电影", "冒险", "犯罪", "灾难"]
		},
		{
			"key": "非凡采集",
			"name": "非凡采集",
			"type": 0,
			"api": "https://api.ffzyapi.com/api.php/provide/vod/from/ffm3u8/at/xml/",
			"searchable": 1,
			"quickSearch": 1,
			"filterable": 1,
			"changeable": 1,
			"categories": ["国产剧", "大陆综艺", "国产动漫", "韩国剧", "喜剧片", "爱情片", "科幻片", "恐怖片", "动作片", "剧情片", "动漫片", "记录片", "短剧"]
		},
		{
			"key": "量子采集",
			"name": "量子采集",
			"type": 1,
			"api": "https://cj.lzcaiji.com/api.php/provide/vod/",
			"searchable": 1,
			"quickSearch": 1,
			"filterable": 1,
			"changeable": 1,
			"categories": ["国产剧", "大陆综艺", "韩国剧", "欧美剧", "喜剧片", "剧情片", "爱情片", "恐怖片", "科幻片", "动漫片", "国产动漫"]
		},
		{
			"key": "drpy_js_低端",
			"name": "欧美日韩",
			"type": 3,
			"playerType": 2,
			"api": "https://ghproxy.net/https://raw.githubusercontent.com/hjdhnx/dr_py/main/libs/drpy2.min.js",
			"ext": "https://ghproxy.net/https://raw.githubusercontent.com/hjdhnx/dr_py/main/js/ddys.js"
		},
		{
			"key": "drpy_js_JRKAN直播",
			"name": "赛事直播",
			"type": 3,
			"api": "https://ghproxy.net/https://raw.githubusercontent.com/hjdhnx/dr_py/main/libs/drpy.min.js",
			"ext": "https://ghproxy.net/https://raw.githubusercontent.com/hjdhnx/dr_py/main/js/JRKAN直播.js"
		},
		{
			"key": "drpy_js_哔哩影视",
			"name": "哔哩影视",
			"type": 3,
			"api": "https://ghproxy.net/https://raw.githubusercontent.com/hjdhnx/dr_py/main/libs/drpy2.min.js",
			"ext": "https://ghproxy.net/https://raw.githubusercontent.com/hjdhnx/dr_py/main/js/哔哩影视.js"
		},
		{
			"key": "drpy_js_斗鱼直播",
			"name": "斗鱼直播",
			"type": 3,
			"searchable": 0,
			"api": "https://ghproxy.net/https://raw.githubusercontent.com/hjdhnx/dr_py/main/libs/drpy2.min.js",
			"ext": "https://ghproxy.net/https://raw.githubusercontent.com/hjdhnx/dr_py/main/js/斗鱼直播.js"
		},
		{
			"key": "drpy_js_虎牙直播",
			"name": "虎牙直播",
			"type": 3,
			"searchable": 0,
			"api": "https://ghproxy.net/https://raw.githubusercontent.com/hjdhnx/dr_py/main/libs/drpy2.min.js",
			"ext": "https://ghproxy.net/https://raw.githubusercontent.com/hjdhnx/dr_py/main/js/虎牙直播.js"
		},
		{
			"key": "drpy_js_相声随身听",
			"name": "相声途听",
			"type": 3,
			"api": "https://ghproxy.net/https://raw.githubusercontent.com/hjdhnx/dr_py/main/libs/drpy2.min.js",
			"ext": "https://ghproxy.net/https://raw.githubusercontent.com/hjdhnx/dr_py/main/js/相声随身听.js",
			"playerType": "2"
		},
		{
			"key": "drpy_js_评书随身听",
			"name": "评书途听",
			"type": 3,
			"api": "https://ghproxy.net/https://raw.githubusercontent.com/hjdhnx/dr_py/main/libs/drpy2.min.js",
			"ext": "https://ghproxy.net/https://raw.githubusercontent.com/hjdhnx/dr_py/main/js/评书随身听.js",
			"playerType": "2"
		},
		{
			"key": "csp_AList",
			"name": "AList云盘",
			"type": 3,
			"playerType": 1,
			"api": "csp_AList",
			"searchable": 1,
			"quickSearch": 1,
			"filterable": 1,
			"ext": {
				"drives": [{
						"name": "Ecve",
						"server": "https://pan.ecve.cn/"
					},
					{
						"name": "小鸭",
						"server": "https://pan.mediy.cn/"
					},
					{
						"name": "秋雨",
						"server": "https://share.qiuyu.org/"
					},
					{
						"name": "小雅",
						"server": "http://alist.xiaoya.pro/"
					}
				]
			}
		},
		{
			"key": "csp_WebDAV",
			"name": "WebDAV",
			"type": 3,
			"api": "csp_WebDAV",
			"searchable": 0,
			"changeable": 0,
			"ext": "https://mirror.ghproxy.com/https://raw.githubusercontent.com/FongMi/CatVodSpider/main/json/webdav.json"
		},
		{
			"key": "csp_Local",
			"name": "本地视频",
			"type": 3,
			"api": "csp_Local",
			"searchable": 0,
			"quickSearch": 0,
			"filterable": 0,
			"changeable": 0,
			"type_flag": 0
		},
		{
			"key": "push_agent",
			"name": "链接推送",
			"type": 3,
			"api": "csp_Push",
			"playerType": 1,
			"searchable": 0,
			"quickSearch": 0,
			"filterable": 0,
			"changeable": 0,
			"ext": "5ed7e8b55cc84468abc8f56395666dc6"
		}
	]
}
